[{"folderName":"the-honor-students-secret-job","mangaName":"The Honor Student's Secret Job"},{"folderName":"tsuyokute-new-saga","mangaName":"Tsuyokute New Saga"},{"folderName":"fullmetal-alchemist","mangaName":"Fullmetal Alchemist"},{"folderName":"jitsu-wa-ore-saikyou-deshita","mangaName":"Jitsu wa Ore, Saikyou Deshita"},{"folderName":"noumin-kanren-no-skill-bakka-agetetara-naze-ka-tsuyoku-natta","mangaName":"Noumin Kanren no Skill Bakka Agetetara Naze ka Tsuyoku Natta"},{"folderName":"haikyuu","mangaName":"Haikyuu!"},{"folderName":"fumetsu-no-anata-e","mangaName":"Fumetsu no Anata e"},{"folderName":"oogamisan-dadamore-desu","mangaName":"Oogami-san, Dadamore Desu"},{"folderName":"sono-mono-nochi-ni-kigatsuitara-s-kyuu-saikyou-yuusha-wazu-no-daibouken","mangaName":"Sono Mono. Nochi ni... ~Kigatsuitara S-kyuu Saikyou!? Yuusha Wazu no Daibouken~"},{"folderName":"himeno-chan-ni-koi-wa-mada-hayai","mangaName":"Himeno-chan ni Koi wa Mada Hayai"},{"folderName":"succubus-vs-lesbian","mangaName":"Succubus vs Lesbian"},{"folderName":"tate-no-yuusha-no-nariagari","mangaName":"Tate no Yuusha no Nariagari"},{"folderName":"manuke-na-fps-player-ga-isekai-e-ochita-baai","mangaName":"Manuke na FPS Player ga Isekai e Ochita Baai"},{"folderName":"doctor-elise","mangaName":"Doctor Elise"},{"folderName":"elf-san-wa-yaserarenai","mangaName":"Elf-san wa Yaserarenai"},{"folderName":"maou-ni-natta-node-dungeon-tsukutte-jingai-musume-to-honobono-suru","mangaName":"Maou ni Natta node, Dungeon Tsukutte Jingai Musume to Honobono suru"},{"folderName":"boku-no-heya-ga-dungeon-no-kyuukeijo-ni-natteshimatta-ken","mangaName":"Boku no Heya ga Dungeon no Kyuukeijo ni Natteshimatta Ken"},{"folderName":"onii-chan-is-done-for","mangaName":"Onii-chan Is Done For"},{"folderName":"fuufu-ijou-koibito-miman","mangaName":"Fuufu Ijou, Koibito Miman"},{"folderName":"hanging-out-with-a-gamer-girl","mangaName":"Hanging Out with a Gamer Girl"},{"folderName":"arifureta-shokugyou-de-sekai-saikyou","mangaName":"Arifureta Shokugyou de Sekai Saikyou"},{"folderName":"yasei-no-last-boss-ga-arawareta","mangaName":"Yasei no Last Boss ga Arawareta"},{"folderName":"a-story-about-treating-a-female-knight-who-has-never-been-treated-as-a-woman-as-a-woman","mangaName":"A Story About Treating a Female Knight, Who Has Never Been Treated as a Woman, as a Woman"},{"folderName":"seirei-gensouki","mangaName":"Seirei Gensouki"},{"folderName":"dogeza-de-tanondemita","mangaName":"Dogeza de Tanondemita"},{"folderName":"sekai-saikyou-no-assassin-isekai-kizoku-ni-tensei-suru","mangaName":"Sekai Saikyou no Assassin, Isekai Kizoku ni Tensei Suru"},{"folderName":"ingoshima","mangaName":"Ingoshima"},{"folderName":"ningen-fushin-no-boukenshatachi-ga-sekai-o-sukuu-youdesu","mangaName":"Ningen Fushin no Boukenshatachi ga Sekai o Sukuu Youdesu"},{"folderName":"darwins-game","mangaName":"Darwin's Game"},{"folderName":"kawaikereba-hentai-demo-suki-ni-natte-kuremasu-ka","mangaName":"Kawaikereba Hentai demo Suki ni Natte Kuremasu ka"},{"folderName":"tou-no-kanri-o-shite-miyou","mangaName":"Tou no Kanri o Shite Miyou"},{"folderName":"pashiri-na-boku-to-koisuru-banchou-san","mangaName":"Pashiri na Boku to Koisuru Banchou-san"},{"folderName":"a-capable-maid","mangaName":"A Capable Maid"},{"folderName":"class-ga-isekai-shoukan-sareta-naka-ore-dake-nokotta-n-desu-ga","mangaName":"Class ga Isekai Shoukan sareta Naka Ore dake Nokotta n desu ga"},{"folderName":"yahari-ore-no-seishun-love-come-wa-machigatteiru-monologue","mangaName":"Yahari Ore no Seishun Love Come wa Machigatteiru -Monologue"},{"folderName":"otome-game-no-hametsu-flag-shika-nai-akuyaku-reijou-ni-tensei-shite-shimatta","mangaName":"Otome Game no Hametsu Flag shika nai Akuyaku Reijou ni Tensei shite shimatta.."},{"folderName":"mushoku-tensei-isekai-ittara-honki-dasu","mangaName":"Mushoku Tensei ~Isekai Ittara Honki Dasu~"},{"folderName":"hinamatsuri","mangaName":"Hinamatsuri"},{"folderName":"nozomanu-fushi-no-boukensha","mangaName":"Nozomanu Fushi no Boukensha"},{"folderName":"isekai-tensei-soudouki","mangaName":"Isekai Tensei Soudouki"},{"folderName":"shaman-king-zero","mangaName":"Shaman King Zero"},{"folderName":"moto-sekai-ichi-i-subchara-ikusei-nikki-hai-player-isekai-wo-kouryakuchuu","mangaName":"Moto Sekai Ichi'i Subchara Ikusei Nikki: Hai Player, Isekai wo Kouryakuchuu"},{"folderName":"kujibiki-tokushou-musou-harem-ken","mangaName":"Kujibiki Tokushou Musou Harem-ken"},{"folderName":"the-hero-who-returned-remains-the-strongest-in-the-modern-world","mangaName":"The Hero Who Returned Remains the Strongest in the Modern World"},{"folderName":"a3","mangaName":"A3!"},{"folderName":"maou-desu-onna-yuusha-no-hahaoya-to-saikon-shita-no-de-onna-yuusha-ga-giri-no-musume-ni-narimashita","mangaName":"Maou Desu. Onna Yuusha no Hahaoya to Saikon Shita no de, Onna Yuusha ga Giri no Musume ni Narimashita"},{"folderName":"overlord","mangaName":"Overlord"},{"folderName":"blue-lock","mangaName":"Blue Lock"},{"folderName":"boukensha-license-wo-hakudatsu-sareta-ossan-dakedo-manamusume-ga-dekita-no-de-nonbiri-jinsei-wo-oukasuru","mangaName":"Boukensha License wo Hakudatsu Sareta Ossan Dakedo, Manamusume ga Dekita no de Nonbiri Jinsei wo Oukasuru"},{"folderName":"otome-danshi-ni-koisuru-otome","mangaName":"Otome Danshi ni Koisuru Otome"},{"folderName":"the-twin-siblings-new-life","mangaName":"The Twin Siblings’ New Life"},{"folderName":"slime-life","mangaName":"Slime Life"},{"folderName":"kemono-jihen","mangaName":"Kemono Jihen"},{"folderName":"boku-no-kanojo-wa-saikoudesu","mangaName":"Boku no Kanojo wa Saikoudesu"},{"folderName":"saving-80-000-gold-coins-in-the-different-world-for-my-old-age","mangaName":"Saving 80,000 Gold Coins in the Different World for My Old Age"},{"folderName":"release-that-witch","mangaName":"Release That Witch"},{"folderName":"tondemo-skill-de-isekai-hourou-meshi","mangaName":"Tondemo Skill de Isekai Hourou Meshi"},{"folderName":"sokushi-cheat-ga-saikyou-sugite-isekai-no-yatsura-ga-marude-aite-ni-naranai-n-desu-ga","mangaName":"Sokushi Cheat ga Saikyou Sugite, Isekai no Yatsura ga Marude Aite ni Naranai n desu ga"},{"folderName":"i-am-a-child-of-this-house","mangaName":"I Am a Child of This House"},{"folderName":"isekai-omotenashi-gohan","mangaName":"Isekai Omotenashi Gohan"},{"folderName":"boku-no-hero-academia","mangaName":"Boku no Hero Academia"},{"folderName":"i-became-a-legend-a-decade-later-after-telling-my-comrades-to-leave-everything-to-me-and-retreat-first","mangaName":"I Became a Legend a Decade Later After Telling My Comrades to Leave Everything to Me and Retreat First"},{"folderName":"player-reborn","mangaName":"Player Reborn"},{"folderName":"remarried-empress","mangaName":"Remarried Empress"},{"folderName":"darling-in-the-franxx","mangaName":"Darling in the FranXX"},{"folderName":"risou-no-himo-seikatsu","mangaName":"Risou no Himo Seikatsu"},{"folderName":"oroka-na-tenshi-wa-akuma-to-odoru","mangaName":"Oroka na Tenshi wa Akuma to Odoru"},{"folderName":"tensei-kizoku-no-isekai-boukenroku-jichou-wo-shiranai-kamigami-no-shito","mangaName":"Tensei Kizoku no Isekai Boukenroku ~Jichou wo Shiranai Kamigami no Shito~"},{"folderName":"iwa-kakeru-climbing-girls","mangaName":"Iwa kakeru! -Climbing Girls"},{"folderName":"i-brought-home-a-succubus-who-failed-to-find-a-job","mangaName":"I Brought Home a Succubus Who Failed to Find a Job"},{"folderName":"tower-of-god","mangaName":"Tower of God"},{"folderName":"moto-saikyou-no-kenshi-wa-isekai-mahou-ni-akogareru","mangaName":"Moto Saikyou no Kenshi wa, Isekai Mahou ni Akogareru"},{"folderName":"the-lady-and-the-beast","mangaName":"The Lady and the Beast"},{"folderName":"infection","mangaName":"Infection"},{"folderName":"nande-koko-ni-sensei-ga","mangaName":"Nande Koko ni Sensei ga!"},{"folderName":"s-rank-monster-no-behemoth-dakedo-neko-to-machigawarete-erufu-musume-no-kishi-pet-toshite-kurashitemasu","mangaName":"S-Rank Monster no Behemoth Dakedo, Neko to Machigawarete Erufu Musume no Kishi (Pet) Toshite Kurashitemasu"},{"folderName":"ryoumin-0-nin-start-no-henkyou-ryoushusama","mangaName":"Ryoumin 0-nin Start no Henkyou Ryoushusama"},{"folderName":"kanojo-okarishimasu","mangaName":"Kanojo, Okarishimasu"},{"folderName":"futoku-no-guild","mangaName":"Futoku no Guild"},{"folderName":"shinka-no-mi","mangaName":"Shinka no Mi"},{"folderName":"tatoeba-last-dungeon-mae-no-mura-no-shounen-ga-joban-no-machi-de-kurasu-youna-monogatari","mangaName":"Tatoeba Last Dungeon Mae no Mura no Shounen ga Joban no Machi de Kurasu Youna Monogatari"},{"folderName":"the-rise-of-the-unemployed-wise-man","mangaName":"The Rise of the Unemployed Wise Man"},{"folderName":"domestic-na-kanojo","mangaName":"Domestic na Kanojo"},{"folderName":"vinland-saga","mangaName":"Vinland Saga"},{"folderName":"seijo-no-maryoku-wa-bannou-desu","mangaName":"Seijo no Maryoku wa Bannou Desu"},{"folderName":"souzai-saishuka-no-isekai-ryokouki","mangaName":"Souzai Saishuka no Isekai Ryokouki"},{"folderName":"mom-please-don-t-come-adventuring-with-me-the-boy-who-was-raised-by-the-ultimate-overprotective-dragon-becomes-an-adventurer-with-his-mother","mangaName":"Mom, Please Don't Come Adventuring With Me! ~The Boy Who Was Raised by the Ultimate Overprotective Dragon, Becomes an Adventurer With His Mother~"},{"folderName":"botsuraku-yotei-nanode-kajishokunin-wo-mezasu","mangaName":"Botsuraku Yotei Nanode, Kajishokunin wo Mezasu"},{"folderName":"chichi-chichi","mangaName":"Chichi Chichi"},{"folderName":"the-small-sage-will-try-her-best-in-the-different-world-from-lv-1","mangaName":"The Small Sage Will Try Her Best in the Different World from Lv. 1"},{"folderName":"gekkan-shoujo-nozakikun","mangaName":"Gekkan Shoujo Nozaki-kun"},{"folderName":"golden-kamuy","mangaName":"Golden Kamuy"},{"folderName":"atsumare-fushigi-kenkyu-bu","mangaName":"Atsumare! Fushigi Kenkyu-bu"},{"folderName":"kubo-san-wa-boku-mobu-wo-yurusanai","mangaName":"Kubo-san wa Boku (Mobu) wo Yurusanai"},{"folderName":"cheat-kusushi-no-slow-life-isekai-ni-tsukurou-drugstore","mangaName":"Cheat Kusushi no Slow Life: Isekai ni Tsukurou Drugstore"},{"folderName":"class-teni-de-ore-dake-haburaretara-doukyuu-harem-tsukuru-koto-ni-shita","mangaName":"Class Teni de Ore dake Haburaretara, Doukyuu Harem Tsukuru Koto ni Shita"},{"folderName":"solo-bug-player","mangaName":"Solo Bug Player"},{"folderName":"kono-yuusha-ga-ore-tueee-kuse-ni-shinchou-sugiru","mangaName":"Kono Yuusha ga Ore TUEEE Kuse ni Shinchou Sugiru"}]