[{"folderName":"ore-no-ie-ga-maryoku-spot-datta-ken-sundeiru-dake-de-sekai-saikyou","mangaName":"Ore no Ie ga Maryoku Spot datta Ken – Sundeiru dake de Sekai Saikyou"},{"folderName":"a-stepmother-s-m-rchen","mangaName":"A Stepmother's Märchen"},{"folderName":"kimi-to-boku-no-saigo-no-senjou-arui-wa-sekai-ga-hajimaru-seisen","mangaName":"Kimi to Boku no Saigo no Senjou, Aruiwa Sekai ga Hajimaru Seisen"},{"folderName":"isekai-kenkokuki","mangaName":"Isekai Kenkokuki"},{"folderName":"suterare-yuusha-wa-kitakuchuu","mangaName":"Suterare Yuusha wa Kitakuchuu"},{"folderName":"boku-no-kanojo-wa-saikoudesu","mangaName":"Boku no Kanojo wa Saikoudesu"},{"folderName":"jiken-jaken","mangaName":"Jiken Jaken"},{"folderName":"moto-sekai-ichi-i-subchara-ikusei-nikki-hai-player-isekai-wo-kouryakuchuu","mangaName":"Moto Sekai Ichi'i Subchara Ikusei Nikki: Hai Player, Isekai wo Kouryakuchuu"},{"folderName":"tomo-chan-wa-onna-no-ko","mangaName":"Tomo-chan wa Onna no ko"},{"folderName":"the-duchess-50-tea-recipes","mangaName":"The Duchess' 50 Tea Recipes"},{"folderName":"tsuyokute-new-saga","mangaName":"Tsuyokute New Saga"},{"folderName":"elf-san-wa-yaserarenai","mangaName":"Elf-san wa Yaserarenai"},{"folderName":"tensei-shitara-slime-datta-ken-mamono-no-kuni-no-arukikata","mangaName":"Tensei Shitara Slime Datta Ken: Mamono no Kuni no Arukikata"},{"folderName":"makenshi-no-maken-niyoru-maken-no-tame-no-harem-life","mangaName":"Makenshi no Maken Niyoru Maken no Tame no Harem Life"},{"folderName":"kawaikereba-hentai-demo-suki-ni-natte-kuremasu-ka","mangaName":"Kawaikereba Hentai demo Suki ni Natte Kuremasu ka"},{"folderName":"the-reincarnated-inferior-magic-swordsman","mangaName":"The Reincarnated Inferior Magic Swordsman"},{"folderName":"jagaaaaaan","mangaName":"Jagaaaaaan"},{"folderName":"my-wife-is-a-demon-queen","mangaName":"My Wife Is a Demon Queen"},{"folderName":"the-story-of-a-girl-with-sanpaku-eyes","mangaName":"The Story of a Girl with Sanpaku Eyes"},{"folderName":"gal-gohan","mangaName":"Gal Gohan"},{"folderName":"kimetsu-no-yaiba","mangaName":"Kimetsu no Yaiba"},{"folderName":"fantasy-bishoujo-juniku-ojisan-to","mangaName":"Fantasy Bishoujo Juniku Ojisan to"},{"folderName":"wotaku-ni-koi-wa-muzukashii","mangaName":"Wotaku ni Koi wa Muzukashii"},{"folderName":"tensei-kizoku-no-isekai-boukenroku-jichou-wo-shiranai-kamigami-no-shito","mangaName":"Tensei Kizoku no Isekai Boukenroku ~Jichou wo Shiranai Kamigami no Shito~"},{"folderName":"kyoukai-meikyuu-to-ikai-no-majutsushi","mangaName":"Kyoukai Meikyuu to Ikai no Majutsushi"},{"folderName":"tensei-pandemic","mangaName":"Tensei Pandemic"},{"folderName":"nanatsu-no-taizai","mangaName":"Nanatsu no Taizai"},{"folderName":"boruto-naruto-next-generations","mangaName":"Boruto: Naruto Next Generations"},{"folderName":"tonari-no-furi-san-ga-tonikaku-kowai","mangaName":"Tonari no Furi-san ga Tonikaku Kowai"},{"folderName":"reincarnated-as-an-aristocrat-with-an-appraisal-skill","mangaName":"Reincarnated as an Aristocrat with an Appraisal Skill"},{"folderName":"no-guard-wife","mangaName":"No Guard Wife"},{"folderName":"seichou-cheat-de-nandemo-dekiru-you-ni-natta-ga-mushoku-dake-wa-yamerarenai-you-desu","mangaName":"Seichou Cheat de Nandemo Dekiru You ni Natta ga, Mushoku Dake wa Yamerarenai You Desu"},{"folderName":"musuko-ga-kawaikute-shikataganai-mazoku-no-hahaoya","mangaName":"Musuko ga Kawaikute Shikataganai Mazoku no Hahaoya"},{"folderName":"berserk-of-gluttony","mangaName":"Berserk of Gluttony"},{"folderName":"ryoumin-0-nin-start-no-henkyou-ryoushusama","mangaName":"Ryoumin 0-nin Start no Henkyou Ryoushusama"},{"folderName":"hataraku-saibou-black","mangaName":"Hataraku Saibou Black"},{"folderName":"may-i-please-ask-you-just-one-last-thing","mangaName":"May I Please Ask You Just One Last Thing"},{"folderName":"kaifuku-jutsushi-no-yarinaoshi","mangaName":"Kaifuku Jutsushi no Yarinaoshi"},{"folderName":"lonely-attack-on-the-different-world","mangaName":"Lonely Attack on the Different World"},{"folderName":"the-last-human","mangaName":"The Last Human"},{"folderName":"the-executed-sage-is-reincarnated-as-a-lich-and-starts-an-all-out-war","mangaName":"The Executed Sage Is Reincarnated as a Lich and Starts an All-Out War"},{"folderName":"world-s-end-harem","mangaName":"World's End Harem"},{"folderName":"shaman-king","mangaName":"Shaman King"},{"folderName":"kawaii-joushi-wo-komarasetai","mangaName":"Kawaii Joushi wo Komarasetai"},{"folderName":"immortal-swordsman-in-the-reverse-world","mangaName":"Immortal Swordsman in the Reverse World"},{"folderName":"isekai-de-kojiin-wo-hiraitakedo-nazeka-darehitori-sudatou-to-shinai-ken","mangaName":"Isekai de Kojiin wo Hiraitakedo, nazeka Darehitori Sudatou to Shinai Ken"},{"folderName":"karakai-jouzu-no-takagi-san","mangaName":"Karakai Jouzu no Takagi-san"},{"folderName":"kumo-desu-ga-nani-ka","mangaName":"Kumo Desu ga, Nani ka"},{"folderName":"raw-hero","mangaName":"RaW Hero"},{"folderName":"sekai-de-ichiban-oppai-ga-suki","mangaName":"Sekai de Ichiban Oppai ga Suki"},{"folderName":"god-of-martial-arts","mangaName":"God of Martial Arts"},{"folderName":"mahoutsukai-no-konyakusha","mangaName":"Mahoutsukai no Konyakusha"},{"folderName":"the-girl-from-random-chatting","mangaName":"The Girl from Random Chatting"},{"folderName":"yofukashi-no-uta","mangaName":"Yofukashi no Uta"},{"folderName":"shi-ni-modori-subete-wo-sukuu-tame-ni-saikyou-he-to-itaru","mangaName":"Shi ni Modori, Subete wo Sukuu Tame ni Saikyou he to Itaru"},{"folderName":"slime-taoshite-300-nen-shiranai-uchi-ni-level-max-ni-nattemashita","mangaName":"Slime Taoshite 300-nen, Shiranai Uchi ni Level MAX ni Nattemashita"},{"folderName":"shounen-chotto-sabotteko","mangaName":"Shounen, Chotto Sabotteko"},{"folderName":"yuusha-ga-shinda","mangaName":"Yuusha ga Shinda"},{"folderName":"handyman-saitou-in-another-world","mangaName":"Handyman Saitou in Another World"},{"folderName":"wanwan-monogatari-kanemochi-no-inu-n-shite-to-wa-itta-ga-fenrir-ni-shiro-to-wa-itte-nee","mangaName":"Wanwan Monogatari ~Kanemochi no Inu n shite to wa Itta ga, Fenrir ni shiro to wa Itte nee!~"},{"folderName":"fumetsu-no-anata-e","mangaName":"Fumetsu no Anata e"},{"folderName":"futoku-no-guild","mangaName":"Futoku no Guild"},{"folderName":"osake-wa-fuufu-ni-natte-kara","mangaName":"Osake wa Fuufu ni Natte Kara"},{"folderName":"ganbare-douki-chan","mangaName":"Ganbare, Douki-chan"},{"folderName":"isekai-wo-seigyo-mahou-de-kirihirake","mangaName":"Isekai wo Seigyo Mahou de Kirihirake"},{"folderName":"shaman-king-red-crimson","mangaName":"Shaman King: Red Crimson"},{"folderName":"konjiki-no-word-master-yuusha-yonin-ni-makikomareta-unique-cheat","mangaName":"Konjiki no Word Master - Yuusha Yonin ni Makikomareta Unique Cheat"},{"folderName":"maseki-gurume-mamono-no-chikara-o-tabeta-ore-wa-saikyou","mangaName":"Maseki Gurume: Mamono no Chikara o Tabeta Ore wa Saikyou"},{"folderName":"dragon-ball-super","mangaName":"Dragon Ball Super"},{"folderName":"ore-dake-haireru-kakushi-dungeon-kossori-kitaete-sekai-saikyou","mangaName":"Ore Dake Haireru Kakushi Dungeon: Kossori Kitaete Sekai Saikyou"},{"folderName":"please-go-home-akutsu-san","mangaName":"Please Go Home, Akutsu-san"},{"folderName":"relife","mangaName":"ReLIFE"},{"folderName":"the-rise-of-the-unemployed-wise-man","mangaName":"The Rise of the Unemployed Wise Man"},{"folderName":"i-swear-i-won-t-bother-you-again","mangaName":"I Swear I Won’t Bother You Again"},{"folderName":"player-reborn","mangaName":"Player Reborn"},{"folderName":"minamoto-kun-monogatari","mangaName":"Minamoto-kun Monogatari"},{"folderName":"the-twin-siblings-new-life","mangaName":"The Twin Siblings’ New Life"},{"folderName":"kami-tachi-ni-hirowareta-otoko","mangaName":"Kami-tachi ni Hirowareta Otoko"},{"folderName":"kengan-omega","mangaName":"Kengan Omega"},{"folderName":"here-u-are","mangaName":"Here U Are"},{"folderName":"ani-no-yome-to-kurashite-imasu","mangaName":"Ani no Yome to Kurashite Imasu"},{"folderName":"mushoku-tensei-isekai-ittara-honki-dasu","mangaName":"Mushoku Tensei ~Isekai Ittara Honki Dasu~"},{"folderName":"potion-danomi-de-ikinobimasu","mangaName":"Potion Danomi de Ikinobimasu"},{"folderName":"maou-no-ore-ga-dorei-elf-wo-yome-ni-shitanda-ga-dou-medereba-ii","mangaName":"Maou no Ore ga Dorei Elf wo Yome ni Shitanda ga, Dou Medereba ii"},{"folderName":"the-strongest-wizard-becomes-a-countryside-guardsman-after-taking-an-arrow-to-the-knee","mangaName":"The Strongest Wizard Becomes a Countryside Guardsman After Taking an Arrow to the Knee"},{"folderName":"wonder-cat-kyuu-chan","mangaName":"Wonder Cat Kyuu-chan"},{"folderName":"nande-koko-ni-sensei-ga","mangaName":"Nande Koko ni Sensei ga!"},{"folderName":"tensei-ouji-wa-daraketai","mangaName":"Tensei Ouji wa Daraketai"},{"folderName":"sekai-saikyou-no-assassin-isekai-kizoku-ni-tensei-suru","mangaName":"Sekai Saikyou no Assassin, Isekai Kizoku ni Tensei Suru"},{"folderName":"kemono-jihen","mangaName":"Kemono Jihen"},{"folderName":"one-piece","mangaName":"One Piece"},{"folderName":"koushaku-reijou-no-tashinami","mangaName":"Koushaku Reijou no Tashinami"},{"folderName":"sukinako-ga-megane-wo-wasureta","mangaName":"Sukinako ga Megane wo Wasureta"},{"folderName":"yuusha-yamemasu","mangaName":"Yuusha, Yamemasu"},{"folderName":"takarakuji-de-40-oku-atatta-ndakedo-isekai-ni-ijuu-suru","mangaName":"Takarakuji de 40 oku Atatta ndakedo Isekai ni Ijuu Suru"},{"folderName":"raise-wa-tanin-ga-ii","mangaName":"Raise wa Tanin ga Ii"},{"folderName":"shinka-no-mi","mangaName":"Shinka no Mi"},{"folderName":"isekai-shihai-no-skill-taker","mangaName":"Isekai Shihai no Skill Taker"},{"folderName":"tensei-shitara-slime-datta-ken","mangaName":"Tensei Shitara Slime Datta Ken"},{"folderName":"this-time-i-will-definitely-be-happy","mangaName":"This Time I Will Definitely Be Happy"}]