[{"folderName":"tensei-shitara-slime-datta-ken-mamono-no-kuni-no-arukikata","mangaName":"Tensei Shitara Slime Datta Ken: Mamono no Kuni no Arukikata"},{"folderName":"ore-wo-suki-nano-wa-omae-dake-ka-yo","mangaName":"Ore wo Suki Nano wa Omae Dake ka yo"},{"folderName":"the-city-of-imprisoned-love","mangaName":"The City of Imprisoned Love"},{"folderName":"tensei-shitara-dragon-no-tamago-datta-ibara-no-dragon-road","mangaName":"Tensei Shitara Dragon no Tamago Datta - Ibara no Dragon Road"},{"folderName":"tensei-pandemic","mangaName":"Tensei Pandemic"},{"folderName":"kenja-no-mago","mangaName":"Kenja no Mago"}]