[{"folderName":"one-punch-man","mangaName":"One Punch-Man"},{"folderName":"sensei-wa-koi-o-oshierarenai","mangaName":"Sensei wa Koi o Oshierarenai"},{"folderName":"yuusha-yamemasu","mangaName":"Yuusha, Yamemasu"},{"folderName":"fumetsu-no-anata-e","mangaName":"Fumetsu no Anata e"},{"folderName":"dad-is-a-hero-mom-is-a-spirit-i-m-a-reincarnator","mangaName":"Dad Is a Hero, Mom Is a Spirit, I'm a Reincarnator"},{"folderName":"ore-to-kawazusan-no-isekai-hourouki","mangaName":"Ore to Kawazu-san no Isekai Hourouki"}]