[{"folderName":"moto-sekai-ichi-i-subchara-ikusei-nikki-hai-player-isekai-wo-kouryakuchuu","mangaName":"Moto Sekai Ichi'i Subchara Ikusei Nikki: Hai Player, Isekai wo Kouryakuchuu"},{"folderName":"death-is-the-only-ending-for-the-villainess","mangaName":"Death Is the Only Ending for the Villainess"},{"folderName":"tales-of-demons-and-gods","mangaName":"Tales of Demons and Gods"},{"folderName":"ore-wo-suki-nano-wa-omae-dake-ka-yo","mangaName":"Ore wo Suki Nano wa Omae Dake ka yo"},{"folderName":"the-labyrinth-raids-of-the-ultimate-tank","mangaName":"The Labyrinth Raids of the Ultimate Tank"},{"folderName":"kimi-wa-008","mangaName":"Kimi wa 008"}]