[{"folderName":"shikimori-s-not-just-a-cutie","mangaName":"Shikimori's Not Just a Cutie"},{"folderName":"please-put-these-on-takamine-san","mangaName":"Please Put These on, Takamine-san"},{"folderName":"a-stepmother-s-m-rchen","mangaName":"A Stepmother's Märchen"},{"folderName":"makikomarete-isekai-teni-suru-yatsu-wa-taitei-cheat","mangaName":"Makikomarete Isekai Teni suru Yatsu wa, Taitei Cheat"},{"folderName":"tenohira-kaitaku-mura-de-isekai-kenkokuki-fueteku-yome-tachi-to-nonbiri-mujintou-life","mangaName":"Tenohira Kaitaku Mura de Isekai Kenkokuki: Fueteku Yome-tachi to Nonbiri Mujintou Life"},{"folderName":"ossan-boukensha-kane-no-zenkou","mangaName":"Ossan Boukensha Kane no Zenkou"}]