[{"folderName":"kobayashi-san-chi-no-maid-dragon","mangaName":"Kobayashi-san Chi no Maid Dragon"},{"folderName":"yurucamp","mangaName":"Yurucamp △"},{"folderName":"saikyou-juzoku-tensei-cheat-majutsushi-no-slow-life","mangaName":"Saikyou Juzoku Tensei: Cheat Majutsushi no Slow Life"},{"folderName":"minamoto-kun-monogatari","mangaName":"Minamoto-kun Monogatari"},{"folderName":"henjo-the-strange-female-high-schooler-amaguri-senko","mangaName":"Henjo - The Strange Female High-Schooler Amaguri Senko"},{"folderName":"my-new-wife-is-forcing-herself-to-smile","mangaName":"My New Wife Is Forcing Herself to Smile"}]