[{"folderName":"kanzen-kaihi-healer-no-kiseki","mangaName":"Kanzen Kaihi Healer no Kiseki"},{"folderName":"omniscient-reader-s-viewpoint","mangaName":"Omniscient Reader's Viewpoint"},{"folderName":"doctor-elise","mangaName":"Doctor Elise"},{"folderName":"kubo-san-wa-boku-mobu-wo-yurusanai","mangaName":"Kubo-san wa Boku (Mobu) wo Yurusanai"},{"folderName":"a-stepmother-s-m-rchen","mangaName":"A Stepmother's Märchen"},{"folderName":"murabito-desu-ga-nani-ka","mangaName":"Murabito Desu ga Nani ka"}]