[{"folderName":"oversimplified-scp","mangaName":"Oversimplified SCP"},{"folderName":"legend","mangaName":"Legend"},{"folderName":"no-guard-wife","mangaName":"No Guard Wife"},{"folderName":"ane-naru-mono","mangaName":"Ane Naru Mono"},{"folderName":"shikkaku-mon-no-saikyou-kenja-sekai-saikyou-no-kenja-ga-sara-ni-tsuyokunaru-tame-ni-tensei-shimashita","mangaName":"Shikkaku Mon no Saikyou Kenja - Sekai Saikyou no Kenja ga Sara ni Tsuyokunaru Tame ni Tensei Shimashita"},{"folderName":"milady-just-wants-to-relax","mangaName":"Milady Just Wants to Relax"}]