[{"folderName":"retired-heroes","mangaName":"Retired Heroes"},{"folderName":"mushoku-no-eiyuu","mangaName":"Mushoku no Eiyuu"},{"folderName":"makikomarete-isekai-teni-suru-yatsu-wa-taitei-cheat","mangaName":"Makikomarete Isekai Teni suru Yatsu wa, Taitei Cheat"},{"folderName":"sekai-de-tadahitori-no-mamono-tsukai-tenshoku-shitara-maou-ni-machigawa-remashita","mangaName":"Sekai de Tadahitori no Mamono Tsukai ~Tenshoku Shitara Maou ni Machigawa Remashita~"},{"folderName":"kawaii-joushi-wo-komarasetai","mangaName":"Kawaii Joushi wo Komarasetai"},{"folderName":"gokushufudou-the-way-of-the-house-husband","mangaName":"Gokushufudou: The Way of the House Husband"}]