[{"folderName":"29-sai-dokushin-wa-isekai-de-jiyuu-ni-ikita-katta","mangaName":"29-sai Dokushin wa Isekai de Jiyuu ni Ikita……katta"},{"folderName":"these-two-will-be-married-in-100-days","mangaName":"These Two Will Be Married In 100 Days"},{"folderName":"saotome-senshu-hitakakusu","mangaName":"Saotome Senshu, Hitakakusu"},{"folderName":"oroka-na-tenshi-wa-akuma-to-odoru","mangaName":"Oroka na Tenshi wa Akuma to Odoru"},{"folderName":"5toubun-no-hanayome","mangaName":"5Toubun no Hanayome"},{"folderName":"gacha-wo-mawashite-nakama-wo-fuyasu-saikyou-no-bishoujo-gundan-wo-tsukuriagero","mangaName":"Gacha wo Mawashite Nakama wo Fuyasu Saikyou no Bishoujo Gundan wo Tsukuriagero"}]