[{"folderName":"the-world-of-otome-games-is-tough-for-mobs","mangaName":"The World of Otome Games Is Tough for Mobs"},{"folderName":"kanojo-okarishimasu","mangaName":"Kanojo, Okarishimasu"},{"folderName":"tonari-no-furi-san-ga-tonikaku-kowai","mangaName":"Tonari no Furi-san ga Tonikaku Kowai"},{"folderName":"rokudou-no-onna-tachi","mangaName":"Rokudou no Onna-tachi"},{"folderName":"i-swear-i-won-t-bother-you-again","mangaName":"I Swear I Won’t Bother You Again"},{"folderName":"beastars","mangaName":"BEASTARS"}]